{
  "generated_utc": "2026-02-27T13:06:17.058095+00:00",
  "generated_at_utc": "2026-02-27T13:06:17.058095+00:00",
  "provider_used": "api",
  "provider_mix": [
    "nwps",
    "raw_nwm"
  ],
  "location": {
    "reach_id": "17682474",
    "location_id": null,
    "gauge_id": "BTEC1"
  },
  "variable": [
    "streamflow"
  ],
  "units": [
    "ft3/s",
    "m3 s-1"
  ],
  "init_times": {
    "analysis": "2026-02-27 12:20:00+00:00",
    "long_range": "2026-02-27 00:00:00+00:00",
    "medium_range": null,
    "short": "2026-02-27 11:00:00+00:00"
  },
  "notes": [
    "Using NWPS observed stageflow as analysis fallback.",
    "NWM medium_range: no data available from reach streamflow endpoint."
  ],
  "ranges": {
    "analysis": {
      "deterministic": [
        {
          "t": "2026-02-26T16:10:00+00:00",
          "v": 207.0
        },
        {
          "t": "2026-02-26T16:15:00+00:00",
          "v": 207.0
        },
        {
          "t": "2026-02-26T16:20:00+00:00",
          "v": 207.0
        },
        {
          "t": "2026-02-26T16:25:00+00:00",
          "v": 207.0
        },
        {
          "t": "2026-02-26T16:30:00+00:00",
          "v": 207.0
        },
        {
          "t": "2026-02-26T16:35:00+00:00",
          "v": 207.0
        },
        {
          "t": "2026-02-26T16:40:00+00:00",
          "v": 207.0
        },
        {
          "t": "2026-02-26T16:45:00+00:00",
          "v": 207.0
        },
        {
          "t": "2026-02-26T16:50:00+00:00",
          "v": 205.0
        },
        {
          "t": "2026-02-26T16:55:00+00:00",
          "v": 207.0
        },
        {
          "t": "2026-02-26T17:00:00+00:00",
          "v": 205.0
        },
        {
          "t": "2026-02-26T17:05:00+00:00",
          "v": 205.0
        },
        {
          "t": "2026-02-26T17:55:00+00:00",
          "v": 205.0
        },
        {
          "t": "2026-02-26T18:00:00+00:00",
          "v": 207.0
        },
        {
          "t": "2026-02-26T18:05:00+00:00",
          "v": 205.0
        },
        {
          "t": "2026-02-26T18:25:00+00:00",
          "v": 205.0
        },
        {
          "t": "2026-02-26T18:30:00+00:00",
          "v": 204.0
        },
        {
          "t": "2026-02-26T18:35:00+00:00",
          "v": 205.0
        },
        {
          "t": "2026-02-26T18:55:00+00:00",
          "v": 205.0
        },
        {
          "t": "2026-02-26T19:00:00+00:00",
          "v": 205.0
        },
        {
          "t": "2026-02-26T19:05:00+00:00",
          "v": 204.0
        },
        {
          "t": "2026-02-26T19:25:00+00:00",
          "v": 204.0
        },
        {
          "t": "2026-02-26T19:30:00+00:00",
          "v": 204.0
        },
        {
          "t": "2026-02-26T19:35:00+00:00",
          "v": 204.0
        },
        {
          "t": "2026-02-26T19:55:00+00:00",
          "v": 204.0
        },
        {
          "t": "2026-02-26T20:00:00+00:00",
          "v": 204.0
        },
        {
          "t": "2026-02-26T20:05:00+00:00",
          "v": 204.0
        },
        {
          "t": "2026-02-26T20:55:00+00:00",
          "v": 204.0
        },
        {
          "t": "2026-02-26T21:00:00+00:00",
          "v": 202.0
        },
        {
          "t": "2026-02-26T21:05:00+00:00",
          "v": 202.0
        },
        {
          "t": "2026-02-26T21:40:00+00:00",
          "v": 202.0
        },
        {
          "t": "2026-02-26T21:45:00+00:00",
          "v": 202.0
        },
        {
          "t": "2026-02-26T21:50:00+00:00",
          "v": 200.0
        },
        {
          "t": "2026-02-26T21:55:00+00:00",
          "v": 202.0
        },
        {
          "t": "2026-02-26T22:00:00+00:00",
          "v": 200.0
        },
        {
          "t": "2026-02-26T22:05:00+00:00",
          "v": 202.0
        },
        {
          "t": "2026-02-27T00:10:00+00:00",
          "v": 200.0
        },
        {
          "t": "2026-02-27T00:15:00+00:00",
          "v": 200.0
        },
        {
          "t": "2026-02-27T00:20:00+00:00",
          "v": 199.0
        },
        {
          "t": "2026-02-27T00:25:00+00:00",
          "v": 200.0
        },
        {
          "t": "2026-02-27T00:30:00+00:00",
          "v": 199.0
        },
        {
          "t": "2026-02-27T00:35:00+00:00",
          "v": 200.0
        },
        {
          "t": "2026-02-27T00:40:00+00:00",
          "v": 199.0
        },
        {
          "t": "2026-02-27T00:45:00+00:00",
          "v": 200.0
        },
        {
          "t": "2026-02-27T00:50:00+00:00",
          "v": 200.0
        },
        {
          "t": "2026-02-27T01:10:00+00:00",
          "v": 200.0
        },
        {
          "t": "2026-02-27T01:15:00+00:00",
          "v": 199.0
        },
        {
          "t": "2026-02-27T01:20:00+00:00",
          "v": 199.0
        },
        {
          "t": "2026-02-27T01:25:00+00:00",
          "v": 199.0
        },
        {
          "t": "2026-02-27T01:30:00+00:00",
          "v": 199.0
        },
        {
          "t": "2026-02-27T01:35:00+00:00",
          "v": 199.0
        },
        {
          "t": "2026-02-27T01:40:00+00:00",
          "v": 199.0
        },
        {
          "t": "2026-02-27T01:45:00+00:00",
          "v": 199.0
        },
        {
          "t": "2026-02-27T01:50:00+00:00",
          "v": 199.0
        },
        {
          "t": "2026-02-27T01:55:00+00:00",
          "v": 199.0
        },
        {
          "t": "2026-02-27T02:00:00+00:00",
          "v": 199.0
        },
        {
          "t": "2026-02-27T02:05:00+00:00",
          "v": 199.0
        },
        {
          "t": "2026-02-27T02:10:00+00:00",
          "v": 199.0
        },
        {
          "t": "2026-02-27T02:15:00+00:00",
          "v": 199.0
        },
        {
          "t": "2026-02-27T02:20:00+00:00",
          "v": 199.0
        },
        {
          "t": "2026-02-27T02:25:00+00:00",
          "v": 199.0
        },
        {
          "t": "2026-02-27T02:30:00+00:00",
          "v": 199.0
        },
        {
          "t": "2026-02-27T02:35:00+00:00",
          "v": 199.0
        },
        {
          "t": "2026-02-27T02:40:00+00:00",
          "v": 199.0
        },
        {
          "t": "2026-02-27T02:45:00+00:00",
          "v": 199.0
        },
        {
          "t": "2026-02-27T02:50:00+00:00",
          "v": 199.0
        },
        {
          "t": "2026-02-27T03:10:00+00:00",
          "v": 199.0
        },
        {
          "t": "2026-02-27T03:15:00+00:00",
          "v": 197.0
        },
        {
          "t": "2026-02-27T03:20:00+00:00",
          "v": 197.0
        },
        {
          "t": "2026-02-27T06:10:00+00:00",
          "v": 193.0
        },
        {
          "t": "2026-02-27T06:15:00+00:00",
          "v": 193.0
        },
        {
          "t": "2026-02-27T06:20:00+00:00",
          "v": 193.0
        },
        {
          "t": "2026-02-27T06:25:00+00:00",
          "v": 193.0
        },
        {
          "t": "2026-02-27T06:30:00+00:00",
          "v": 193.0
        },
        {
          "t": "2026-02-27T06:35:00+00:00",
          "v": 193.0
        },
        {
          "t": "2026-02-27T06:40:00+00:00",
          "v": 193.0
        },
        {
          "t": "2026-02-27T06:45:00+00:00",
          "v": 193.0
        },
        {
          "t": "2026-02-27T06:50:00+00:00",
          "v": 193.0
        },
        {
          "t": "2026-02-27T06:55:00+00:00",
          "v": 193.0
        },
        {
          "t": "2026-02-27T07:00:00+00:00",
          "v": 193.0
        },
        {
          "t": "2026-02-27T07:05:00+00:00",
          "v": 193.0
        },
        {
          "t": "2026-02-27T07:10:00+00:00",
          "v": 193.0
        },
        {
          "t": "2026-02-27T07:15:00+00:00",
          "v": 193.0
        },
        {
          "t": "2026-02-27T07:20:00+00:00",
          "v": 193.0
        },
        {
          "t": "2026-02-27T07:25:00+00:00",
          "v": 193.0
        },
        {
          "t": "2026-02-27T07:30:00+00:00",
          "v": 193.0
        },
        {
          "t": "2026-02-27T07:35:00+00:00",
          "v": 193.0
        },
        {
          "t": "2026-02-27T08:10:00+00:00",
          "v": 192.0
        },
        {
          "t": "2026-02-27T08:15:00+00:00",
          "v": 192.0
        },
        {
          "t": "2026-02-27T08:20:00+00:00",
          "v": 192.0
        },
        {
          "t": "2026-02-27T08:40:00+00:00",
          "v": 192.0
        },
        {
          "t": "2026-02-27T08:45:00+00:00",
          "v": 190.0
        },
        {
          "t": "2026-02-27T08:50:00+00:00",
          "v": 192.0
        },
        {
          "t": "2026-02-27T08:55:00+00:00",
          "v": 190.0
        },
        {
          "t": "2026-02-27T09:00:00+00:00",
          "v": 192.0
        },
        {
          "t": "2026-02-27T09:05:00+00:00",
          "v": 190.0
        },
        {
          "t": "2026-02-27T09:10:00+00:00",
          "v": 192.0
        },
        {
          "t": "2026-02-27T09:15:00+00:00",
          "v": 190.0
        },
        {
          "t": "2026-02-27T09:20:00+00:00",
          "v": 190.0
        },
        {
          "t": "2026-02-27T09:25:00+00:00",
          "v": 190.0
        },
        {
          "t": "2026-02-27T09:30:00+00:00",
          "v": 190.0
        },
        {
          "t": "2026-02-27T09:35:00+00:00",
          "v": 190.0
        },
        {
          "t": "2026-02-27T10:40:00+00:00",
          "v": 190.0
        },
        {
          "t": "2026-02-27T10:45:00+00:00",
          "v": 190.0
        },
        {
          "t": "2026-02-27T10:50:00+00:00",
          "v": 190.0
        },
        {
          "t": "2026-02-27T11:10:00+00:00",
          "v": 190.0
        },
        {
          "t": "2026-02-27T11:15:00+00:00",
          "v": 188.0
        },
        {
          "t": "2026-02-27T11:20:00+00:00",
          "v": 188.0
        },
        {
          "t": "2026-02-27T11:25:00+00:00",
          "v": 188.0
        },
        {
          "t": "2026-02-27T11:30:00+00:00",
          "v": 188.0
        },
        {
          "t": "2026-02-27T11:35:00+00:00",
          "v": 188.0
        },
        {
          "t": "2026-02-27T11:40:00+00:00",
          "v": 188.0
        },
        {
          "t": "2026-02-27T11:45:00+00:00",
          "v": 188.0
        },
        {
          "t": "2026-02-27T11:50:00+00:00",
          "v": 188.0
        },
        {
          "t": "2026-02-27T11:55:00+00:00",
          "v": 188.0
        },
        {
          "t": "2026-02-27T12:00:00+00:00",
          "v": 188.0
        },
        {
          "t": "2026-02-27T12:05:00+00:00",
          "v": 188.0
        },
        {
          "t": "2026-02-27T12:10:00+00:00",
          "v": 188.0
        },
        {
          "t": "2026-02-27T12:15:00+00:00",
          "v": 188.0
        },
        {
          "t": "2026-02-27T12:20:00+00:00",
          "v": 187.0
        }
      ]
    },
    "short": {
      "deterministic": [
        {
          "t": "2026-02-27T12:00:00+00:00",
          "v": 191.75
        },
        {
          "t": "2026-02-27T13:00:00+00:00",
          "v": 197.75999450683594
        },
        {
          "t": "2026-02-27T14:00:00+00:00",
          "v": 206.94000244140625
        },
        {
          "t": "2026-02-27T15:00:00+00:00",
          "v": 219.29998779296875
        },
        {
          "t": "2026-02-27T16:00:00+00:00",
          "v": 235.1999969482422
        },
        {
          "t": "2026-02-27T17:00:00+00:00",
          "v": 252.14999389648438
        },
        {
          "t": "2026-02-27T18:00:00+00:00",
          "v": 268.3899841308594
        },
        {
          "t": "2026-02-27T19:00:00+00:00",
          "v": 281.4599914550781
        },
        {
          "t": "2026-02-27T20:00:00+00:00",
          "v": 288.5199890136719
        },
        {
          "t": "2026-02-27T21:00:00+00:00",
          "v": 289.92999267578125
        },
        {
          "t": "2026-02-27T22:00:00+00:00",
          "v": 286.3999938964844
        },
        {
          "t": "2026-02-27T23:00:00+00:00",
          "v": 280.04998779296875
        },
        {
          "t": "2026-02-28T00:00:00+00:00",
          "v": 271.57000732421875
        },
        {
          "t": "2026-02-28T01:00:00+00:00",
          "v": 263.0899963378906
        },
        {
          "t": "2026-02-28T02:00:00+00:00",
          "v": 257.44000244140625
        },
        {
          "t": "2026-02-28T03:00:00+00:00",
          "v": 253.9099884033203
        },
        {
          "t": "2026-02-28T04:00:00+00:00",
          "v": 252.14999389648438
        },
        {
          "t": "2026-02-28T05:00:00+00:00",
          "v": 252.14999389648438
        }
      ]
    },
    "medium_range": {
      "p10": [],
      "p50": [],
      "p90": []
    },
    "long_range": {
      "p10": [
        {
          "t": "2026-02-27T06:00:00+00:00",
          "v": 210.1199951171875
        },
        {
          "t": "2026-02-27T12:00:00+00:00",
          "v": 220.3600006103516
        },
        {
          "t": "2026-02-27T18:00:00+00:00",
          "v": 219.6949890136719
        },
        {
          "t": "2026-02-28T00:00:00+00:00",
          "v": 216.4799957275391
        },
        {
          "t": "2026-02-28T06:00:00+00:00",
          "v": 212.9499969482422
        },
        {
          "t": "2026-02-28T12:00:00+00:00",
          "v": 209.76998901367188
        },
        {
          "t": "2026-02-28T18:00:00+00:00",
          "v": 206.94000244140625
        },
        {
          "t": "2026-03-01T00:00:00+00:00",
          "v": 203.76998901367188
        },
        {
          "t": "2026-03-01T06:00:00+00:00",
          "v": 200.58999633789062
        },
        {
          "t": "2026-03-01T12:00:00+00:00",
          "v": 197.4099884033203
        },
        {
          "t": "2026-03-01T18:00:00+00:00",
          "v": 194.5800018310547
        },
        {
          "t": "2026-03-02T00:00:00+00:00",
          "v": 191.75999450683597
        },
        {
          "t": "2026-03-02T06:00:00+00:00",
          "v": 188.92999267578125
        },
        {
          "t": "2026-03-02T12:00:00+00:00",
          "v": 186.1449996948242
        },
        {
          "t": "2026-03-02T18:00:00+00:00",
          "v": 183.81599884033204
        },
        {
          "t": "2026-03-03T00:00:00+00:00",
          "v": 186.7100021362305
        },
        {
          "t": "2026-03-03T06:00:00+00:00",
          "v": 188.0489944458008
        },
        {
          "t": "2026-03-03T12:00:00+00:00",
          "v": 181.19799957275393
        },
        {
          "t": "2026-03-03T18:00:00+00:00",
          "v": 175.79600219726564
        },
        {
          "t": "2026-03-04T00:00:00+00:00",
          "v": 172.2979965209961
        },
        {
          "t": "2026-03-04T06:00:00+00:00",
          "v": 169.7219940185547
        },
        {
          "t": "2026-03-04T12:00:00+00:00",
          "v": 167.2519943237305
        },
        {
          "t": "2026-03-04T18:00:00+00:00",
          "v": 165.16699829101563
        },
        {
          "t": "2026-03-05T00:00:00+00:00",
          "v": 163.04700164794923
        },
        {
          "t": "2026-03-05T06:00:00+00:00",
          "v": 160.8919937133789
        },
        {
          "t": "2026-03-05T12:00:00+00:00",
          "v": 158.80799713134766
        },
        {
          "t": "2026-03-05T18:00:00+00:00",
          "v": 157.08200225830078
        },
        {
          "t": "2026-03-06T00:00:00+00:00",
          "v": 154.96199340820314
        },
        {
          "t": "2026-03-06T06:00:00+00:00",
          "v": 153.19300231933593
        },
        {
          "t": "2026-03-06T12:00:00+00:00",
          "v": 151.143994140625
        },
        {
          "t": "2026-03-06T18:00:00+00:00",
          "v": 149.41799926757812
        },
        {
          "t": "2026-03-07T00:00:00+00:00",
          "v": 147.61299438476564
        },
        {
          "t": "2026-03-07T06:00:00+00:00",
          "v": 145.4929992675781
        },
        {
          "t": "2026-03-07T12:00:00+00:00",
          "v": 143.44400329589843
        },
        {
          "t": "2026-03-07T18:00:00+00:00",
          "v": 141.718994140625
        },
        {
          "t": "2026-03-08T00:00:00+00:00",
          "v": 139.91399078369142
        },
        {
          "t": "2026-03-08T06:00:00+00:00",
          "v": 138.15399627685548
        },
        {
          "t": "2026-03-08T12:00:00+00:00",
          "v": 136.41899261474612
        },
        {
          "t": "2026-03-08T18:00:00+00:00",
          "v": 134.69399719238282
        },
        {
          "t": "2026-03-09T00:00:00+00:00",
          "v": 132.8889938354492
        },
        {
          "t": "2026-03-09T06:00:00+00:00",
          "v": 131.12000274658203
        },
        {
          "t": "2026-03-09T12:00:00+00:00",
          "v": 129.74499969482423
        },
        {
          "t": "2026-03-09T18:00:00+00:00",
          "v": 128.05499801635742
        },
        {
          "t": "2026-03-10T00:00:00+00:00",
          "v": 126.5650001525879
        },
        {
          "t": "2026-03-10T06:00:00+00:00",
          "v": 124.80399780273437
        },
        {
          "t": "2026-03-10T12:00:00+00:00",
          "v": 123.3589942932129
        },
        {
          "t": "2026-03-10T18:00:00+00:00",
          "v": 122.29899673461915
        },
        {
          "t": "2026-03-11T00:00:00+00:00",
          "v": 120.52899932861328
        },
        {
          "t": "2026-03-11T06:00:00+00:00",
          "v": 119.71399993896485
        },
        {
          "t": "2026-03-11T12:00:00+00:00",
          "v": 118.61799545288086
        },
        {
          "t": "2026-03-11T18:00:00+00:00",
          "v": 117.24299926757813
        },
        {
          "t": "2026-03-12T00:00:00+00:00",
          "v": 115.83299560546875
        },
        {
          "t": "2026-03-12T06:00:00+00:00",
          "v": 114.73799819946291
        },
        {
          "t": "2026-03-12T12:00:00+00:00",
          "v": 115.2709976196289
        },
        {
          "t": "2026-03-12T18:00:00+00:00",
          "v": 115.4119972229004
        },
        {
          "t": "2026-03-13T00:00:00+00:00",
          "v": 114.02799911499024
        },
        {
          "t": "2026-03-13T06:00:00+00:00",
          "v": 112.4059959411621
        },
        {
          "t": "2026-03-13T12:00:00+00:00",
          "v": 109.62099609375001
        },
        {
          "t": "2026-03-13T18:00:00+00:00",
          "v": 107.28299942016602
        },
        {
          "t": "2026-03-14T00:00:00+00:00",
          "v": 105.8729965209961
        },
        {
          "t": "2026-03-14T06:00:00+00:00",
          "v": 104.49800033569336
        },
        {
          "t": "2026-03-14T12:00:00+00:00",
          "v": 103.1229965209961
        },
        {
          "t": "2026-03-14T18:00:00+00:00",
          "v": 102.09799880981447
        },
        {
          "t": "2026-03-15T00:00:00+00:00",
          "v": 101.0030014038086
        },
        {
          "t": "2026-03-15T06:00:00+00:00",
          "v": 100.22299499511719
        },
        {
          "t": "2026-03-15T12:00:00+00:00",
          "v": 99.16299743652344
        },
        {
          "t": "2026-03-15T18:00:00+00:00",
          "v": 98.38199844360352
        },
        {
          "t": "2026-03-16T00:00:00+00:00",
          "v": 97.64600067138673
        },
        {
          "t": "2026-03-16T06:00:00+00:00",
          "v": 97.8909996032715
        },
        {
          "t": "2026-03-16T12:00:00+00:00",
          "v": 98.95300064086915
        },
        {
          "t": "2026-03-16T18:00:00+00:00",
          "v": 101.56599655151368
        },
        {
          "t": "2026-03-17T00:00:00+00:00",
          "v": 103.22499771118164
        },
        {
          "t": "2026-03-17T06:00:00+00:00",
          "v": 104.10499877929688
        },
        {
          "t": "2026-03-17T12:00:00+00:00",
          "v": 102.37399368286134
        },
        {
          "t": "2026-03-17T18:00:00+00:00",
          "v": 97.8589973449707
        },
        {
          "t": "2026-03-18T00:00:00+00:00",
          "v": 94.11499938964845
        },
        {
          "t": "2026-03-18T06:00:00+00:00",
          "v": 91.74899520874024
        },
        {
          "t": "2026-03-18T12:00:00+00:00",
          "v": 90.12399673461915
        },
        {
          "t": "2026-03-18T18:00:00+00:00",
          "v": 89.13199768066407
        },
        {
          "t": "2026-03-19T00:00:00+00:00",
          "v": 88.00100021362304
        },
        {
          "t": "2026-03-19T06:00:00+00:00",
          "v": 87.58000183105469
        },
        {
          "t": "2026-03-19T12:00:00+00:00",
          "v": 86.55499649047852
        },
        {
          "t": "2026-03-19T18:00:00+00:00",
          "v": 85.60099868774415
        },
        {
          "t": "2026-03-20T00:00:00+00:00",
          "v": 84.61200103759766
        },
        {
          "t": "2026-03-20T06:00:00+00:00",
          "v": 83.58699645996094
        },
        {
          "t": "2026-03-20T12:00:00+00:00",
          "v": 82.92199935913087
        },
        {
          "t": "2026-03-20T18:00:00+00:00",
          "v": 82.03900146484375
        },
        {
          "t": "2026-03-21T00:00:00+00:00",
          "v": 81.57599563598633
        },
        {
          "t": "2026-03-21T06:00:00+00:00",
          "v": 80.7639976501465
        },
        {
          "t": "2026-03-21T12:00:00+00:00",
          "v": 79.70400009155273
        },
        {
          "t": "2026-03-21T18:00:00+00:00",
          "v": 79.1439956665039
        },
        {
          "t": "2026-03-22T00:00:00+00:00",
          "v": 78.61399765014649
        },
        {
          "t": "2026-03-22T06:00:00+00:00",
          "v": 78.25799865722657
        },
        {
          "t": "2026-03-22T12:00:00+00:00",
          "v": 77.05600051879883
        },
        {
          "t": "2026-03-22T18:00:00+00:00",
          "v": 76.06400146484376
        },
        {
          "t": "2026-03-23T00:00:00+00:00",
          "v": 75.15199737548828
        },
        {
          "t": "2026-03-23T06:00:00+00:00",
          "v": 74.69199981689454
        },
        {
          "t": "2026-03-23T12:00:00+00:00",
          "v": 78.86200180053712
        },
        {
          "t": "2026-03-23T18:00:00+00:00",
          "v": 87.58099441528321
        },
        {
          "t": "2026-03-24T00:00:00+00:00",
          "v": 112.40699691772461
        },
        {
          "t": "2026-03-24T06:00:00+00:00",
          "v": 125.29699630737306
        },
        {
          "t": "2026-03-24T12:00:00+00:00",
          "v": 109.2629997253418
        },
        {
          "t": "2026-03-24T18:00:00+00:00",
          "v": 92.34399490356446
        },
        {
          "t": "2026-03-25T00:00:00+00:00",
          "v": 85.66899795532227
        },
        {
          "t": "2026-03-25T06:00:00+00:00",
          "v": 83.27300033569335
        },
        {
          "t": "2026-03-25T12:00:00+00:00",
          "v": 77.72899627685547
        },
        {
          "t": "2026-03-25T18:00:00+00:00",
          "v": 78.36099624633789
        },
        {
          "t": "2026-03-26T00:00:00+00:00",
          "v": 82.42799911499023
        },
        {
          "t": "2026-03-26T06:00:00+00:00",
          "v": 90.93799629211426
        },
        {
          "t": "2026-03-26T12:00:00+00:00",
          "v": 96.12599906921386
        },
        {
          "t": "2026-03-26T18:00:00+00:00",
          "v": 86.62299842834473
        },
        {
          "t": "2026-03-27T00:00:00+00:00",
          "v": 74.09199829101563
        },
        {
          "t": "2026-03-27T06:00:00+00:00",
          "v": 68.61199798583985
        },
        {
          "t": "2026-03-27T12:00:00+00:00",
          "v": 67.20599975585938
        },
        {
          "t": "2026-03-27T18:00:00+00:00",
          "v": 68.08599891662598
        },
        {
          "t": "2026-03-28T00:00:00+00:00",
          "v": 70.94799575805663
        },
        {
          "t": "2026-03-28T06:00:00+00:00",
          "v": 82.95799560546875
        },
        {
          "t": "2026-03-28T12:00:00+00:00",
          "v": 108.4119956970215
        },
        {
          "t": "2026-03-28T18:00:00+00:00",
          "v": 127.27699966430666
        },
        {
          "t": "2026-03-29T00:00:00+00:00",
          "v": 124.16899337768555
        }
      ],
      "p50": [
        {
          "t": "2026-02-27T06:00:00+00:00",
          "v": 210.1199951171875
        },
        {
          "t": "2026-02-27T12:00:00+00:00",
          "v": 220.36000061035156
        },
        {
          "t": "2026-02-27T18:00:00+00:00",
          "v": 219.83499145507812
        },
        {
          "t": "2026-02-28T00:00:00+00:00",
          "v": 216.47999572753906
        },
        {
          "t": "2026-02-28T06:00:00+00:00",
          "v": 212.9499969482422
        },
        {
          "t": "2026-02-28T12:00:00+00:00",
          "v": 209.76998901367188
        },
        {
          "t": "2026-02-28T18:00:00+00:00",
          "v": 206.94000244140625
        },
        {
          "t": "2026-03-01T00:00:00+00:00",
          "v": 203.76998901367188
        },
        {
          "t": "2026-03-01T06:00:00+00:00",
          "v": 200.58999633789062
        },
        {
          "t": "2026-03-01T12:00:00+00:00",
          "v": 197.4099884033203
        },
        {
          "t": "2026-03-01T18:00:00+00:00",
          "v": 194.5800018310547
        },
        {
          "t": "2026-03-02T00:00:00+00:00",
          "v": 191.75999450683594
        },
        {
          "t": "2026-03-02T06:00:00+00:00",
          "v": 188.92999267578125
        },
        {
          "t": "2026-03-02T12:00:00+00:00",
          "v": 186.28499603271484
        },
        {
          "t": "2026-03-02T18:00:00+00:00",
          "v": 184.5199966430664
        },
        {
          "t": "2026-03-03T00:00:00+00:00",
          "v": 193.3499984741211
        },
        {
          "t": "2026-03-03T06:00:00+00:00",
          "v": 198.6449966430664
        },
        {
          "t": "2026-03-03T12:00:00+00:00",
          "v": 186.98999786376953
        },
        {
          "t": "2026-03-03T18:00:00+00:00",
          "v": 178.33999633789062
        },
        {
          "t": "2026-03-04T00:00:00+00:00",
          "v": 173.56999969482422
        },
        {
          "t": "2026-03-04T06:00:00+00:00",
          "v": 170.5699920654297
        },
        {
          "t": "2026-03-04T12:00:00+00:00",
          "v": 168.0999984741211
        },
        {
          "t": "2026-03-04T18:00:00+00:00",
          "v": 166.15499877929688
        },
        {
          "t": "2026-03-05T00:00:00+00:00",
          "v": 164.03499603271484
        },
        {
          "t": "2026-03-05T06:00:00+00:00",
          "v": 161.73999786376953
        },
        {
          "t": "2026-03-05T12:00:00+00:00",
          "v": 159.79999542236328
        },
        {
          "t": "2026-03-05T18:00:00+00:00",
          "v": 158.20999908447266
        },
        {
          "t": "2026-03-06T00:00:00+00:00",
          "v": 156.08999633789062
        },
        {
          "t": "2026-03-06T06:00:00+00:00",
          "v": 154.3249969482422
        },
        {
          "t": "2026-03-06T12:00:00+00:00",
          "v": 152.55999755859375
        },
        {
          "t": "2026-03-06T18:00:00+00:00",
          "v": 150.97000122070312
        },
        {
          "t": "2026-03-07T00:00:00+00:00",
          "v": 149.02499389648438
        },
        {
          "t": "2026-03-07T06:00:00+00:00",
          "v": 146.90499877929688
        },
        {
          "t": "2026-03-07T12:00:00+00:00",
          "v": 145.13999938964844
        },
        {
          "t": "2026-03-07T18:00:00+00:00",
          "v": 143.55499267578125
        },
        {
          "t": "2026-03-08T00:00:00+00:00",
          "v": 141.60999298095703
        },
        {
          "t": "2026-03-08T06:00:00+00:00",
          "v": 139.8499984741211
        },
        {
          "t": "2026-03-08T12:00:00+00:00",
          "v": 138.25499725341797
        },
        {
          "t": "2026-03-08T18:00:00+00:00",
          "v": 136.6699981689453
        },
        {
          "t": "2026-03-09T00:00:00+00:00",
          "v": 134.7249984741211
        },
        {
          "t": "2026-03-09T06:00:00+00:00",
          "v": 132.95999908447266
        },
        {
          "t": "2026-03-09T12:00:00+00:00",
          "v": 131.7249984741211
        },
        {
          "t": "2026-03-09T18:00:00+00:00",
          "v": 130.31499862670898
        },
        {
          "t": "2026-03-10T00:00:00+00:00",
          "v": 128.54500198364258
        },
        {
          "t": "2026-03-10T06:00:00+00:00",
          "v": 126.77999877929688
        },
        {
          "t": "2026-03-10T12:00:00+00:00",
          "v": 125.19499588012695
        },
        {
          "t": "2026-03-10T18:00:00+00:00",
          "v": 124.1349983215332
        },
        {
          "t": "2026-03-11T00:00:00+00:00",
          "v": 122.36499786376953
        },
        {
          "t": "2026-03-11T06:00:00+00:00",
          "v": 121.12999725341797
        },
        {
          "t": "2026-03-11T12:00:00+00:00",
          "v": 119.88999557495117
        },
        {
          "t": "2026-03-11T18:00:00+00:00",
          "v": 118.65499877929688
        },
        {
          "t": "2026-03-12T00:00:00+00:00",
          "v": 117.2449951171875
        },
        {
          "t": "2026-03-12T06:00:00+00:00",
          "v": 116.0099983215332
        },
        {
          "t": "2026-03-12T12:00:00+00:00",
          "v": 115.83499908447266
        },
        {
          "t": "2026-03-12T18:00:00+00:00",
          "v": 116.53999710083008
        },
        {
          "t": "2026-03-13T00:00:00+00:00",
          "v": 115.29999923706055
        },
        {
          "t": "2026-03-13T06:00:00+00:00",
          "v": 112.82999801635742
        },
        {
          "t": "2026-03-13T12:00:00+00:00",
          "v": 110.18499755859375
        },
        {
          "t": "2026-03-13T18:00:00+00:00",
          "v": 108.41499710083008
        },
        {
          "t": "2026-03-14T00:00:00+00:00",
          "v": 107.00499725341797
        },
        {
          "t": "2026-03-14T06:00:00+00:00",
          "v": 105.77000045776367
        },
        {
          "t": "2026-03-14T12:00:00+00:00",
          "v": 104.53499603271484
        },
        {
          "t": "2026-03-14T18:00:00+00:00",
          "v": 103.64999771118164
        },
        {
          "t": "2026-03-15T00:00:00+00:00",
          "v": 102.41500091552734
        },
        {
          "t": "2026-03-15T06:00:00+00:00",
          "v": 101.35499572753906
        },
        {
          "t": "2026-03-15T12:00:00+00:00",
          "v": 100.29499816894531
        },
        {
          "t": "2026-03-15T18:00:00+00:00",
          "v": 99.22999954223633
        },
        {
          "t": "2026-03-16T00:00:00+00:00",
          "v": 98.3499984741211
        },
        {
          "t": "2026-03-16T06:00:00+00:00",
          "v": 98.17499923706055
        },
        {
          "t": "2026-03-16T12:00:00+00:00",
          "v": 104.8849983215332
        },
        {
          "t": "2026-03-16T18:00:00+00:00",
          "v": 122.18999862670898
        },
        {
          "t": "2026-03-17T00:00:00+00:00",
          "v": 134.72499465942383
        },
        {
          "t": "2026-03-17T06:00:00+00:00",
          "v": 141.96499633789062
        },
        {
          "t": "2026-03-17T12:00:00+00:00",
          "v": 137.54999160766602
        },
        {
          "t": "2026-03-17T18:00:00+00:00",
          "v": 117.77499771118164
        },
        {
          "t": "2026-03-18T00:00:00+00:00",
          "v": 103.29499816894531
        },
        {
          "t": "2026-03-18T06:00:00+00:00",
          "v": 95.70499801635742
        },
        {
          "t": "2026-03-18T12:00:00+00:00",
          "v": 91.81999588012695
        },
        {
          "t": "2026-03-18T18:00:00+00:00",
          "v": 89.69999694824219
        },
        {
          "t": "2026-03-19T00:00:00+00:00",
          "v": 88.28499984741211
        },
        {
          "t": "2026-03-19T06:00:00+00:00",
          "v": 87.58000183105469
        },
        {
          "t": "2026-03-19T12:00:00+00:00",
          "v": 86.69499588012695
        },
        {
          "t": "2026-03-19T18:00:00+00:00",
          "v": 86.16499710083008
        },
        {
          "t": "2026-03-20T00:00:00+00:00",
          "v": 85.45999908447266
        },
        {
          "t": "2026-03-20T06:00:00+00:00",
          "v": 84.57499694824219
        },
        {
          "t": "2026-03-20T12:00:00+00:00",
          "v": 84.04999923706055
        },
        {
          "t": "2026-03-20T18:00:00+00:00",
          "v": 83.875
        },
        {
          "t": "2026-03-21T00:00:00+00:00",
          "v": 84.39999771118164
        },
        {
          "t": "2026-03-21T06:00:00+00:00",
          "v": 84.57999801635742
        },
        {
          "t": "2026-03-21T12:00:00+00:00",
          "v": 83.52000045776367
        },
        {
          "t": "2026-03-21T18:00:00+00:00",
          "v": 83.5199966430664
        },
        {
          "t": "2026-03-22T00:00:00+00:00",
          "v": 85.1099967956543
        },
        {
          "t": "2026-03-22T06:00:00+00:00",
          "v": 86.16999816894531
        },
        {
          "t": "2026-03-22T12:00:00+00:00",
          "v": 84.39999771118164
        },
        {
          "t": "2026-03-22T18:00:00+00:00",
          "v": 82.27999877929688
        },
        {
          "t": "2026-03-23T00:00:00+00:00",
          "v": 80.5199966430664
        },
        {
          "t": "2026-03-23T06:00:00+00:00",
          "v": 82.45999908447266
        },
        {
          "t": "2026-03-23T12:00:00+00:00",
          "v": 104.71000289916992
        },
        {
          "t": "2026-03-23T18:00:00+00:00",
          "v": 151.14499282836914
        },
        {
          "t": "2026-03-24T00:00:00+00:00",
          "v": 279.5149955749512
        },
        {
          "t": "2026-03-24T06:00:00+00:00",
          "v": 348.20498275756836
        },
        {
          "t": "2026-03-24T12:00:00+00:00",
          "v": 272.2749900817871
        },
        {
          "t": "2026-03-24T18:00:00+00:00",
          "v": 190.51999282836914
        },
        {
          "t": "2026-03-25T00:00:00+00:00",
          "v": 161.3849983215332
        },
        {
          "t": "2026-03-25T06:00:00+00:00",
          "v": 152.20499801635742
        },
        {
          "t": "2026-03-25T12:00:00+00:00",
          "v": 128.7249984741211
        },
        {
          "t": "2026-03-25T18:00:00+00:00",
          "v": 134.72499465942383
        },
        {
          "t": "2026-03-26T00:00:00+00:00",
          "v": 157.8599967956543
        },
        {
          "t": "2026-03-26T06:00:00+00:00",
          "v": 204.64998817443848
        },
        {
          "t": "2026-03-26T12:00:00+00:00",
          "v": 233.42999839782715
        },
        {
          "t": "2026-03-26T18:00:00+00:00",
          "v": 188.75499153137207
        },
        {
          "t": "2026-03-27T00:00:00+00:00",
          "v": 128.89999389648438
        },
        {
          "t": "2026-03-27T06:00:00+00:00",
          "v": 102.93999481201172
        },
        {
          "t": "2026-03-27T12:00:00+00:00",
          "v": 94.47000122070312
        },
        {
          "t": "2026-03-27T18:00:00+00:00",
          "v": 93.2299976348877
        },
        {
          "t": "2026-03-28T00:00:00+00:00",
          "v": 94.81999588012695
        },
        {
          "t": "2026-03-28T06:00:00+00:00",
          "v": 102.58999633789062
        },
        {
          "t": "2026-03-28T12:00:00+00:00",
          "v": 118.29999923706055
        },
        {
          "t": "2026-03-28T18:00:00+00:00",
          "v": 130.66499710083008
        },
        {
          "t": "2026-03-29T00:00:00+00:00",
          "v": 141.96499252319336
        }
      ],
      "p90": [
        {
          "t": "2026-02-27T06:00:00+00:00",
          "v": 210.1199951171875
        },
        {
          "t": "2026-02-27T12:00:00+00:00",
          "v": 220.36000061035156
        },
        {
          "t": "2026-02-27T18:00:00+00:00",
          "v": 219.97499389648436
        },
        {
          "t": "2026-02-28T00:00:00+00:00",
          "v": 216.47999572753906
        },
        {
          "t": "2026-02-28T06:00:00+00:00",
          "v": 212.9499969482422
        },
        {
          "t": "2026-02-28T12:00:00+00:00",
          "v": 209.76998901367188
        },
        {
          "t": "2026-02-28T18:00:00+00:00",
          "v": 206.94000244140625
        },
        {
          "t": "2026-03-01T00:00:00+00:00",
          "v": 203.76998901367188
        },
        {
          "t": "2026-03-01T06:00:00+00:00",
          "v": 200.58999633789062
        },
        {
          "t": "2026-03-01T12:00:00+00:00",
          "v": 197.4099884033203
        },
        {
          "t": "2026-03-01T18:00:00+00:00",
          "v": 194.5800018310547
        },
        {
          "t": "2026-03-02T00:00:00+00:00",
          "v": 191.75999450683594
        },
        {
          "t": "2026-03-02T06:00:00+00:00",
          "v": 188.92999267578125
        },
        {
          "t": "2026-03-02T12:00:00+00:00",
          "v": 186.42499237060548
        },
        {
          "t": "2026-03-02T18:00:00+00:00",
          "v": 185.22399444580077
        },
        {
          "t": "2026-03-03T00:00:00+00:00",
          "v": 199.9899948120117
        },
        {
          "t": "2026-03-03T06:00:00+00:00",
          "v": 209.24099884033205
        },
        {
          "t": "2026-03-03T12:00:00+00:00",
          "v": 192.78199615478516
        },
        {
          "t": "2026-03-03T18:00:00+00:00",
          "v": 180.8839904785156
        },
        {
          "t": "2026-03-04T00:00:00+00:00",
          "v": 174.84200286865234
        },
        {
          "t": "2026-03-04T06:00:00+00:00",
          "v": 171.4179901123047
        },
        {
          "t": "2026-03-04T12:00:00+00:00",
          "v": 168.94800262451173
        },
        {
          "t": "2026-03-04T18:00:00+00:00",
          "v": 167.14299926757812
        },
        {
          "t": "2026-03-05T00:00:00+00:00",
          "v": 165.02299041748046
        },
        {
          "t": "2026-03-05T06:00:00+00:00",
          "v": 162.58800201416017
        },
        {
          "t": "2026-03-05T12:00:00+00:00",
          "v": 160.79199371337893
        },
        {
          "t": "2026-03-05T18:00:00+00:00",
          "v": 159.33799591064454
        },
        {
          "t": "2026-03-06T00:00:00+00:00",
          "v": 157.21799926757814
        },
        {
          "t": "2026-03-06T06:00:00+00:00",
          "v": 155.45699157714844
        },
        {
          "t": "2026-03-06T12:00:00+00:00",
          "v": 153.9760009765625
        },
        {
          "t": "2026-03-06T18:00:00+00:00",
          "v": 152.52200317382812
        },
        {
          "t": "2026-03-07T00:00:00+00:00",
          "v": 150.43699340820314
        },
        {
          "t": "2026-03-07T06:00:00+00:00",
          "v": 148.31699829101564
        },
        {
          "t": "2026-03-07T12:00:00+00:00",
          "v": 146.83599548339845
        },
        {
          "t": "2026-03-07T18:00:00+00:00",
          "v": 145.3909912109375
        },
        {
          "t": "2026-03-08T00:00:00+00:00",
          "v": 143.30599517822264
        },
        {
          "t": "2026-03-08T06:00:00+00:00",
          "v": 141.5460006713867
        },
        {
          "t": "2026-03-08T12:00:00+00:00",
          "v": 140.09100189208985
        },
        {
          "t": "2026-03-08T18:00:00+00:00",
          "v": 138.64599914550783
        },
        {
          "t": "2026-03-09T00:00:00+00:00",
          "v": 136.56100311279297
        },
        {
          "t": "2026-03-09T06:00:00+00:00",
          "v": 134.79999542236328
        },
        {
          "t": "2026-03-09T12:00:00+00:00",
          "v": 133.70499725341796
        },
        {
          "t": "2026-03-09T18:00:00+00:00",
          "v": 132.57499923706055
        },
        {
          "t": "2026-03-10T00:00:00+00:00",
          "v": 130.52500381469727
        },
        {
          "t": "2026-03-10T06:00:00+00:00",
          "v": 128.75599975585936
        },
        {
          "t": "2026-03-10T12:00:00+00:00",
          "v": 127.030997467041
        },
        {
          "t": "2026-03-10T18:00:00+00:00",
          "v": 125.97099990844727
        },
        {
          "t": "2026-03-11T00:00:00+00:00",
          "v": 124.20099639892578
        },
        {
          "t": "2026-03-11T06:00:00+00:00",
          "v": 122.5459945678711
        },
        {
          "t": "2026-03-11T12:00:00+00:00",
          "v": 121.16199569702148
        },
        {
          "t": "2026-03-11T18:00:00+00:00",
          "v": 120.06699829101562
        },
        {
          "t": "2026-03-12T00:00:00+00:00",
          "v": 118.65699462890626
        },
        {
          "t": "2026-03-12T06:00:00+00:00",
          "v": 117.28199844360351
        },
        {
          "t": "2026-03-12T12:00:00+00:00",
          "v": 116.39900054931641
        },
        {
          "t": "2026-03-12T18:00:00+00:00",
          "v": 117.66799697875977
        },
        {
          "t": "2026-03-13T00:00:00+00:00",
          "v": 116.57199935913086
        },
        {
          "t": "2026-03-13T06:00:00+00:00",
          "v": 113.25400009155274
        },
        {
          "t": "2026-03-13T12:00:00+00:00",
          "v": 110.74899902343749
        },
        {
          "t": "2026-03-13T18:00:00+00:00",
          "v": 109.54699478149415
        },
        {
          "t": "2026-03-14T00:00:00+00:00",
          "v": 108.13699798583984
        },
        {
          "t": "2026-03-14T06:00:00+00:00",
          "v": 107.04200057983398
        },
        {
          "t": "2026-03-14T12:00:00+00:00",
          "v": 105.9469955444336
        },
        {
          "t": "2026-03-14T18:00:00+00:00",
          "v": 105.20199661254884
        },
        {
          "t": "2026-03-15T00:00:00+00:00",
          "v": 103.82700042724609
        },
        {
          "t": "2026-03-15T06:00:00+00:00",
          "v": 102.48699645996093
        },
        {
          "t": "2026-03-15T12:00:00+00:00",
          "v": 101.4269989013672
        },
        {
          "t": "2026-03-15T18:00:00+00:00",
          "v": 100.07800064086913
        },
        {
          "t": "2026-03-16T00:00:00+00:00",
          "v": 99.05399627685546
        },
        {
          "t": "2026-03-16T06:00:00+00:00",
          "v": 98.4589988708496
        },
        {
          "t": "2026-03-16T12:00:00+00:00",
          "v": 110.81699600219727
        },
        {
          "t": "2026-03-16T18:00:00+00:00",
          "v": 142.81400070190432
        },
        {
          "t": "2026-03-17T00:00:00+00:00",
          "v": 166.22499160766603
        },
        {
          "t": "2026-03-17T06:00:00+00:00",
          "v": 179.82499389648436
        },
        {
          "t": "2026-03-17T12:00:00+00:00",
          "v": 172.7259895324707
        },
        {
          "t": "2026-03-17T18:00:00+00:00",
          "v": 137.69099807739258
        },
        {
          "t": "2026-03-18T00:00:00+00:00",
          "v": 112.4749969482422
        },
        {
          "t": "2026-03-18T06:00:00+00:00",
          "v": 99.66100082397462
        },
        {
          "t": "2026-03-18T12:00:00+00:00",
          "v": 93.51599502563477
        },
        {
          "t": "2026-03-18T18:00:00+00:00",
          "v": 90.2679962158203
        },
        {
          "t": "2026-03-19T00:00:00+00:00",
          "v": 88.56899948120117
        },
        {
          "t": "2026-03-19T06:00:00+00:00",
          "v": 87.58000183105469
        },
        {
          "t": "2026-03-19T12:00:00+00:00",
          "v": 86.83499526977539
        },
        {
          "t": "2026-03-19T18:00:00+00:00",
          "v": 86.728995513916
        },
        {
          "t": "2026-03-20T00:00:00+00:00",
          "v": 86.30799713134765
        },
        {
          "t": "2026-03-20T06:00:00+00:00",
          "v": 85.56299743652345
        },
        {
          "t": "2026-03-20T12:00:00+00:00",
          "v": 85.17799911499024
        },
        {
          "t": "2026-03-20T18:00:00+00:00",
          "v": 85.71099853515625
        },
        {
          "t": "2026-03-21T00:00:00+00:00",
          "v": 87.22399978637695
        },
        {
          "t": "2026-03-21T06:00:00+00:00",
          "v": 88.39599838256837
        },
        {
          "t": "2026-03-21T12:00:00+00:00",
          "v": 87.33600082397462
        },
        {
          "t": "2026-03-21T18:00:00+00:00",
          "v": 87.89599761962891
        },
        {
          "t": "2026-03-22T00:00:00+00:00",
          "v": 91.60599594116212
        },
        {
          "t": "2026-03-22T06:00:00+00:00",
          "v": 94.08199768066406
        },
        {
          "t": "2026-03-22T12:00:00+00:00",
          "v": 91.74399490356446
        },
        {
          "t": "2026-03-22T18:00:00+00:00",
          "v": 88.49599609375001
        },
        {
          "t": "2026-03-23T00:00:00+00:00",
          "v": 85.88799591064453
        },
        {
          "t": "2026-03-23T06:00:00+00:00",
          "v": 90.22799835205078
        },
        {
          "t": "2026-03-23T12:00:00+00:00",
          "v": 130.55800399780273
        },
        {
          "t": "2026-03-23T18:00:00+00:00",
          "v": 214.7089912414551
        },
        {
          "t": "2026-03-24T00:00:00+00:00",
          "v": 446.62299423217775
        },
        {
          "t": "2026-03-24T06:00:00+00:00",
          "v": 571.1129692077637
        },
        {
          "t": "2026-03-24T12:00:00+00:00",
          "v": 435.28698043823243
        },
        {
          "t": "2026-03-24T18:00:00+00:00",
          "v": 288.6959907531739
        },
        {
          "t": "2026-03-25T00:00:00+00:00",
          "v": 237.10099868774415
        },
        {
          "t": "2026-03-25T06:00:00+00:00",
          "v": 221.1369956970215
        },
        {
          "t": "2026-03-25T12:00:00+00:00",
          "v": 179.72100067138672
        },
        {
          "t": "2026-03-25T18:00:00+00:00",
          "v": 191.08899307250977
        },
        {
          "t": "2026-03-26T00:00:00+00:00",
          "v": 233.29199447631837
        },
        {
          "t": "2026-03-26T06:00:00+00:00",
          "v": 318.36198005676266
        },
        {
          "t": "2026-03-26T12:00:00+00:00",
          "v": 370.73399772644046
        },
        {
          "t": "2026-03-26T18:00:00+00:00",
          "v": 290.8869846343994
        },
        {
          "t": "2026-03-27T00:00:00+00:00",
          "v": 183.70798950195314
        },
        {
          "t": "2026-03-27T06:00:00+00:00",
          "v": 137.2679916381836
        },
        {
          "t": "2026-03-27T12:00:00+00:00",
          "v": 121.73400268554687
        },
        {
          "t": "2026-03-27T18:00:00+00:00",
          "v": 118.37399635314941
        },
        {
          "t": "2026-03-28T00:00:00+00:00",
          "v": 118.69199600219727
        },
        {
          "t": "2026-03-28T06:00:00+00:00",
          "v": 122.22199707031251
        },
        {
          "t": "2026-03-28T12:00:00+00:00",
          "v": 128.18800277709963
        },
        {
          "t": "2026-03-28T18:00:00+00:00",
          "v": 134.05299453735353
        },
        {
          "t": "2026-03-29T00:00:00+00:00",
          "v": 159.76099166870117
        }
      ]
    }
  }
}
